{
  "sector": "Beauvais Solitude",
  "problems": [
    {
      "name": "L'Enfant du Sable",
      "url": "https://bleau.info/beauvaisest/1210.html",
      "grade": "7b+",
      "alt_grade": null,
      "first_ascensionist": "Alexis Allayaud",
      "styles": [
        "traversée"
      ],
      "rating": null
    },
    {
      "name": "La Bombe Humaine",
      "url": "https://bleau.info/beauvaisest/1209.html",
      "grade": "7b+",
      "alt_grade": null,
      "first_ascensionist": "Alexis Allayaud",
      "styles": [
        "jeté",
        "dalle"
      ],
      "rating": 2.0
    },
    {
      "name": "Choux Blanc",
      "url": "https://bleau.info/beauvaisest/307527.html",
      "grade": "7b",
      "alt_grade": null,
      "first_ascensionist": "Sébastien Frigault",
      "styles": [
        "dévers",
        "départ assis"
      ],
      "rating": 4.0
    },
    {
      "name": "La Cémentation",
      "url": "https://bleau.info/beauvaisest/13130.html",
      "grade": "7b",
      "alt_grade": null,
      "first_ascensionist": "Dominique Yvorel",
      "styles": [
        "surplomb",
        "réta",
        "expo"
      ],
      "rating": null
    },
    {
      "name": "Princesse Grenouille",
      "url": "https://bleau.info/beauvaisest/312007.html",
      "grade": "7b",
      "alt_grade": null,
      "first_ascensionist": "kaiss richard",
      "styles": [
        "traversée d-g",
        "départ assis"
      ],
      "rating": 4.0
    },
    {
      "name": "Rupture d'Anévrisme",
      "url": "https://bleau.info/beauvaisest/13134.html",
      "grade": "7b",
      "alt_grade": null,
      "first_ascensionist": "Dominique Yvorel",
      "styles": [
        "surplomb",
        "dalle",
        "départ assis"
      ],
      "rating": null
    },
    {
      "name": "Duo des Noms",
      "url": "https://bleau.info/beauvaisest/13063.html",
      "grade": "7a+",
      "alt_grade": null,
      "first_ascensionist": "Frédéric Buc",
      "styles": [
        "traversée d-g"
      ],
      "rating": 3.0
    },
    {
      "name": "Fa Dièse",
      "url": "https://bleau.info/beauvaisest/13065.html",
      "grade": "7a+",
      "alt_grade": null,
      "first_ascensionist": "Dominique Yvorel",
      "styles": [
        "traversée g-d",
        "bidoigts",
        "aplats"
      ],
      "rating": null
    },
    {
      "name": "Le Cochonnet",
      "url": "https://bleau.info/beauvaisest/13058.html",
      "grade": "7a+",
      "alt_grade": null,
      "first_ascensionist": "Dominique Yvorel",
      "styles": [
        "traversée d-g",
        "aplats",
        "fissure"
      ],
      "rating": null
    },
    {
      "name": "Le Dévirginisateur",
      "url": "https://bleau.info/beauvaisest/13129.html",
      "grade": "7a+",
      "alt_grade": null,
      "first_ascensionist": "Dominique Yvorel",
      "styles": [
        "traversée d-g"
      ],
      "rating": null
    },
    {
      "name": "Arachnophobie",
      "url": "https://bleau.info/beauvaisest/13083.html",
      "grade": "7a",
      "alt_grade": null,
      "first_ascensionist": "Dominique Yvorel",
      "styles": [
        "surplomb",
        "inversées",
        "départ assis"
      ],
      "rating": null
    },
    {
      "name": "Bâbord",
      "url": "https://bleau.info/beauvaisest/13124.html",
      "grade": "7a",
      "alt_grade": "6c+",
      "first_ascensionist": "Dominique Yvorel",
      "styles": [
        "mur",
        "aplats",
        "expo"
      ],
      "rating": 2.0
    },
    {
      "name": "Boletus Satanus",
      "url": "https://bleau.info/beauvaisest/1208.html",
      "grade": "7a",
      "alt_grade": null,
      "first_ascensionist": "Eric Allayaud",
      "styles": [
        "traversée"
      ],
      "rating": null
    },
    {
      "name": "C'est Royal (droite)",
      "url": "https://bleau.info/beauvaisest/13132.html",
      "grade": "7a",
      "alt_grade": null,
      "first_ascensionist": "Dominique Yvorel",
      "styles": [
        "proue"
      ],
      "rating": null
    },
    {
      "name": "Attention Trav Bleau",
      "url": "https://bleau.info/beauvaisest/13064.html",
      "grade": "6c+",
      "alt_grade": null,
      "first_ascensionist": "Dominique Yvorel",
      "styles": [
        "traversée g-d"
      ],
      "rating": null
    },
    {
      "name": "Achille",
      "url": "https://bleau.info/beauvaisest/13089.html",
      "grade": "6c",
      "alt_grade": null,
      "first_ascensionist": "Dominique Yvorel",
      "styles": [
        "dévers"
      ],
      "rating": 3.5
    },
    {
      "name": "Amanita",
      "url": "https://bleau.info/beauvaisest/6758.html",
      "grade": "6c",
      "alt_grade": null,
      "first_ascensionist": null,
      "styles": [
        "traversée"
      ],
      "rating": null
    },
    {
      "name": "Archultime",
      "url": "https://bleau.info/beauvaisest/6752.html",
      "grade": "6c",
      "alt_grade": null,
      "first_ascensionist": null,
      "styles": [
        "pilier"
      ],
      "rating": null
    },
    {
      "name": "Bourrinator",
      "url": "https://bleau.info/beauvaisest/6748.html",
      "grade": "6c",
      "alt_grade": null,
      "first_ascensionist": null,
      "styles": [
        "traversée d-g"
      ],
      "rating": null
    },
    {
      "name": "C'est Royal",
      "url": "https://bleau.info/beauvaisest/13131.html",
      "grade": "6c",
      "alt_grade": null,
      "first_ascensionist": "Dominique Yvorel",
      "styles": [
        "proue"
      ],
      "rating": null
    },
    {
      "name": "Hémisphère Gauche",
      "url": "https://bleau.info/beauvaisest/13135.html",
      "grade": "6c",
      "alt_grade": null,
      "first_ascensionist": "Dominique Yvorel",
      "styles": [
        "mur",
        "aplats"
      ],
      "rating": null
    },
    {
      "name": "Ici Commence l'Éternité",
      "url": "https://bleau.info/beauvaisest/6773.html",
      "grade": "6c",
      "alt_grade": null,
      "first_ascensionist": null,
      "styles": [
        "mur"
      ],
      "rating": null
    },
    {
      "name": "L'Ami Hostile (assis)",
      "url": "https://bleau.info/beauvaisest/307455.html",
      "grade": "6c",
      "alt_grade": null,
      "first_ascensionist": null,
      "styles": [
        "mur",
        "départ assis"
      ],
      "rating": null
    },
    {
      "name": "L'Embrayage",
      "url": "https://bleau.info/beauvaisest/13046.html",
      "grade": "6c",
      "alt_grade": null,
      "first_ascensionist": "Franck Martinez",
      "styles": [
        "mur",
        "réglettes"
      ],
      "rating": 2.5
    },
    {
      "name": "Le Retour de Tourneboule",
      "url": "https://bleau.info/beauvaisest/15380.html",
      "grade": "6c",
      "alt_grade": null,
      "first_ascensionist": "Pepito",
      "styles": [
        "traversée g-d"
      ],
      "rating": 3.5
    },
    {
      "name": "Le Rêve de Russ Meyer",
      "url": "https://bleau.info/beauvaisest/13137.html",
      "grade": "6c",
      "alt_grade": null,
      "first_ascensionist": "Dominique Yvorel",
      "styles": [
        "proue",
        "départ assis"
      ],
      "rating": null
    },
    {
      "name": "Les Caprices d'Éole",
      "url": "https://bleau.info/beauvaisest/6755.html",
      "grade": "6c",
      "alt_grade": null,
      "first_ascensionist": null,
      "styles": [
        "traversée g-d"
      ],
      "rating": 3.0
    },
    {
      "name": "Ragnarök",
      "url": "https://bleau.info/beauvaisest/6770.html",
      "grade": "6c",
      "alt_grade": null,
      "first_ascensionist": null,
      "styles": [
        "traversée d-g"
      ],
      "rating": null
    },
    {
      "name": "Tournecourt",
      "url": "https://bleau.info/beauvaisest/13099.html",
      "grade": "6c",
      "alt_grade": null,
      "first_ascensionist": "Dominique Yvorel",
      "styles": [
        "dévers",
        "réglettes",
        "réta"
      ],
      "rating": null
    },
    {
      "name": "Bouse de Là",
      "url": "https://bleau.info/beauvaisest/13075.html",
      "grade": "6b+",
      "alt_grade": null,
      "first_ascensionist": "Dominique Yvorel",
      "styles": [
        "traversée",
        "boucle"
      ],
      "rating": null
    },
    {
      "name": "Two Edges",
      "url": "https://bleau.info/beauvaisest/13114.html",
      "grade": "6b+",
      "alt_grade": null,
      "first_ascensionist": "Dominique Yvorel",
      "styles": [
        "traversée d-g",
        "départ assis"
      ],
      "rating": 3.0
    },
    {
      "name": "50%",
      "url": "https://bleau.info/beauvaisest/13093.html",
      "grade": "6b",
      "alt_grade": null,
      "first_ascensionist": "Dominique Yvorel",
      "styles": [
        "arête",
        "dévers",
        "départ assis"
      ],
      "rating": null
    },
    {
      "name": "Boule de Pus",
      "url": "https://bleau.info/beauvaisest/13084.html",
      "grade": "6b",
      "alt_grade": null,
      "first_ascensionist": "Dominique Yvorel",
      "styles": [
        "dévers",
        "expo"
      ],
      "rating": null
    },
    {
      "name": "Chêne Là",
      "url": "https://bleau.info/beauvaisest/13088.html",
      "grade": "6b",
      "alt_grade": null,
      "first_ascensionist": null,
      "styles": [
        "dévers",
        "expo"
      ],
      "rating": 3.5
    },
    {
      "name": "La Croisade du Pivot",
      "url": "https://bleau.info/beauvaisest/13044.html",
      "grade": "6b",
      "alt_grade": null,
      "first_ascensionist": "Franck Martinez",
      "styles": [
        "traversée g-d"
      ],
      "rating": null
    },
    {
      "name": "Palmolive",
      "url": "https://bleau.info/beauvaisest/13090.html",
      "grade": "6b",
      "alt_grade": null,
      "first_ascensionist": "Dominique Yvorel",
      "styles": [
        "dévers",
        "jeté"
      ],
      "rating": 3.0
    },
    {
      "name": "Penchant Fatal",
      "url": "https://bleau.info/beauvaisest/13079.html",
      "grade": "6b",
      "alt_grade": null,
      "first_ascensionist": "Dominique Yvorel",
      "styles": [
        "mur",
        "arête",
        "expo"
      ],
      "rating": null
    },
    {
      "name": "Le Tomahawk",
      "url": "https://bleau.info/beauvaisest/6764.html",
      "grade": "6a+",
      "alt_grade": null,
      "first_ascensionist": null,
      "styles": [
        "mur"
      ],
      "rating": 3.0
    },
    {
      "name": "Mobydick",
      "url": "https://bleau.info/beauvaisest/6772.html",
      "grade": "6a+",
      "alt_grade": null,
      "first_ascensionist": null,
      "styles": [
        "réta"
      ],
      "rating": null
    },
    {
      "name": "Pas Touche!",
      "url": "https://bleau.info/beauvaisest/13110.html",
      "grade": "6a+",
      "alt_grade": null,
      "first_ascensionist": "Dominique Yvorel",
      "styles": [
        "traversée g-d",
        "surplomb"
      ],
      "rating": null
    },
    {
      "name": "Senteur d'Opium",
      "url": "https://bleau.info/beauvaisest/6771.html",
      "grade": "6a+",
      "alt_grade": null,
      "first_ascensionist": null,
      "styles": [
        "dalle"
      ],
      "rating": null
    },
    {
      "name": "Tourneboule",
      "url": "https://bleau.info/beauvaisest/13098.html",
      "grade": "6a+",
      "alt_grade": null,
      "first_ascensionist": "Dominique Yvorel",
      "styles": [
        "traversée d-g",
        "inversées",
        "réta"
      ],
      "rating": 4.0
    },
    {
      "name": "Tourneboule (direct)",
      "url": "https://bleau.info/beauvaisest/307526.html",
      "grade": "6a+",
      "alt_grade": null,
      "first_ascensionist": null,
      "styles": [
        "dévers",
        "départ assis"
      ],
      "rating": null
    },
    {
      "name": "Tu Tires et tu Pointes",
      "url": "https://bleau.info/beauvaisest/13057.html",
      "grade": "6a+",
      "alt_grade": null,
      "first_ascensionist": "Franck Martinez",
      "styles": [
        "traversée g-d",
        "arête"
      ],
      "rating": null
    },
    {
      "name": "Zizania",
      "url": "https://bleau.info/beauvaisest/6756.html",
      "grade": "6a+",
      "alt_grade": null,
      "first_ascensionist": null,
      "styles": [
        "traversée d-g"
      ],
      "rating": null
    },
    {
      "name": "Afrique  (assis)",
      "url": "https://bleau.info/beauvaisest/307508.html",
      "grade": "6a",
      "alt_grade": null,
      "first_ascensionist": "Pepito, Blokeur",
      "styles": [
        "mur",
        "départ assis"
      ],
      "rating": null
    },
    {
      "name": "Bas-Hic",
      "url": "https://bleau.info/beauvaisest/13062.html",
      "grade": "6a",
      "alt_grade": null,
      "first_ascensionist": "Franck Martinez",
      "styles": [
        "surplomb",
        "départ assis"
      ],
      "rating": null
    },
    {
      "name": "Bien Mur (assis)",
      "url": "https://bleau.info/beauvaisest/116740.html",
      "grade": "6a",
      "alt_grade": null,
      "first_ascensionist": null,
      "styles": [
        "mur",
        "départ assis"
      ],
      "rating": null
    },
    {
      "name": "Boletus",
      "url": "https://bleau.info/beauvaisest/6757.html",
      "grade": "6a",
      "alt_grade": null,
      "first_ascensionist": null,
      "styles": [
        "traversée d-g"
      ],
      "rating": null
    },
    {
      "name": "Charter pour le Hongrois",
      "url": "https://bleau.info/beauvaisest/13127.html",
      "grade": "6a",
      "alt_grade": "7b",
      "first_ascensionist": "Dominique Yvorel",
      "styles": [
        "traversée d-g"
      ],
      "rating": null
    },
    {
      "name": "Coup de Fatigue (assis)",
      "url": "https://bleau.info/beauvaisest/307461.html",
      "grade": "6a",
      "alt_grade": null,
      "first_ascensionist": "Pepito, Blokeur",
      "styles": [
        "pilier",
        "départ assis"
      ],
      "rating": null
    },
    {
      "name": "Dos au Mur (droite)",
      "url": "https://bleau.info/beauvaisest/25085.html",
      "grade": "6a",
      "alt_grade": null,
      "first_ascensionist": null,
      "styles": [
        "mur"
      ],
      "rating": null
    },
    {
      "name": "Drapeau Rouge",
      "url": "https://bleau.info/beauvaisest/13112.html",
      "grade": "6a",
      "alt_grade": null,
      "first_ascensionist": null,
      "styles": [
        "dalle"
      ],
      "rating": 3.0
    },
    {
      "name": "L'Âge Sombre",
      "url": "https://bleau.info/beauvaisest/6754.html",
      "grade": "6a",
      "alt_grade": null,
      "first_ascensionist": null,
      "styles": [
        "dévers"
      ],
      "rating": null
    },
    {
      "name": "La Confiscation (assis)",
      "url": "https://bleau.info/beauvaisest/307457.html",
      "grade": "6a",
      "alt_grade": null,
      "first_ascensionist": "Pepito, Blokeur",
      "styles": [
        "pilier",
        "départ assis"
      ],
      "rating": null
    },
    {
      "name": "Le Mur du Feu",
      "url": "https://bleau.info/beauvaisest/13100.html",
      "grade": "6a",
      "alt_grade": null,
      "first_ascensionist": "Dominique Yvorel",
      "styles": [
        "mur"
      ],
      "rating": 2.0
    },
    {
      "name": "Le Paquebot",
      "url": "https://bleau.info/beauvaisest/13117.html",
      "grade": "6a",
      "alt_grade": null,
      "first_ascensionist": "Dominique Yvorel",
      "styles": [
        "mur",
        "proue"
      ],
      "rating": 3.0
    },
    {
      "name": "Lunarios",
      "url": "https://bleau.info/beauvaisest/6767.html",
      "grade": "6a",
      "alt_grade": null,
      "first_ascensionist": null,
      "styles": [
        "pilier"
      ],
      "rating": 4.0
    },
    {
      "name": "Pierre de Taille (droite)",
      "url": "https://bleau.info/beauvaisest/6751.html",
      "grade": "6a",
      "alt_grade": null,
      "first_ascensionist": null,
      "styles": [
        "arête"
      ],
      "rating": 2.0
    },
    {
      "name": "Tête Dure (assis)",
      "url": "https://bleau.info/beauvaisest/307465.html",
      "grade": "6a",
      "alt_grade": null,
      "first_ascensionist": "Pepito, Blokeur",
      "styles": [
        "pilier",
        "départ assis"
      ],
      "rating": null
    },
    {
      "name": "Tiquodrome",
      "url": "https://bleau.info/beauvaisest/6768.html",
      "grade": "6a",
      "alt_grade": null,
      "first_ascensionist": null,
      "styles": [
        "traversée d-g"
      ],
      "rating": null
    },
    {
      "name": "Tu Tires et tu Pointes (direct)",
      "url": "https://bleau.info/beauvaisest/13059.html",
      "grade": "6a",
      "alt_grade": null,
      "first_ascensionist": "Franck Martinez",
      "styles": [
        "proue",
        "départ assis"
      ],
      "rating": null
    },
    {
      "name": "Un Autre Temps",
      "url": "https://bleau.info/beauvaisest/13094.html",
      "grade": "6a",
      "alt_grade": null,
      "first_ascensionist": null,
      "styles": [
        "dalle"
      ],
      "rating": 4.0
    },
    {
      "name": "Avril en Mars",
      "url": "https://bleau.info/beauvaisest/13138.html",
      "grade": "5+",
      "alt_grade": null,
      "first_ascensionist": "Dominique Yvorel",
      "styles": [
        "traversée d-g",
        "départ assis"
      ],
      "rating": null
    },
    {
      "name": "Bascule",
      "url": "https://bleau.info/beauvaisest/13082.html",
      "grade": "5+",
      "alt_grade": null,
      "first_ascensionist": "Dominique Yvorel",
      "styles": [
        "arête",
        "aplats",
        "départ assis"
      ],
      "rating": null
    },
    {
      "name": "Bastingage",
      "url": "https://bleau.info/beauvaisest/13120.html",
      "grade": "5+",
      "alt_grade": null,
      "first_ascensionist": "Dominique Yvorel",
      "styles": [
        "traversée g-d"
      ],
      "rating": null
    },
    {
      "name": "Bis",
      "url": "https://bleau.info/beauvaisest/13051.html",
      "grade": "5+",
      "alt_grade": "5",
      "first_ascensionist": "Franck Martinez",
      "styles": [
        "traversée g-d"
      ],
      "rating": null
    },
    {
      "name": "Cérébral",
      "url": "https://bleau.info/beauvaisest/13133.html",
      "grade": "5+",
      "alt_grade": null,
      "first_ascensionist": "Dominique Yvorel",
      "styles": [
        "surplomb",
        "dalle"
      ],
      "rating": null
    },
    {
      "name": "Crash Prohibited",
      "url": "https://bleau.info/beauvaisest/13087.html",
      "grade": "5+",
      "alt_grade": null,
      "first_ascensionist": "Dominique Yvorel",
      "styles": [
        "mur",
        "expo"
      ],
      "rating": null
    },
    {
      "name": "Éole (assis)",
      "url": "https://bleau.info/beauvaisest/307453.html",
      "grade": "5+",
      "alt_grade": null,
      "first_ascensionist": "Pepito, Blokeur",
      "styles": [
        "mur",
        "départ assis"
      ],
      "rating": null
    },
    {
      "name": "Gaillard d'Avant",
      "url": "https://bleau.info/beauvaisest/13118.html",
      "grade": "5+",
      "alt_grade": null,
      "first_ascensionist": "Dominique Yvorel",
      "styles": [
        "mur"
      ],
      "rating": null
    },
    {
      "name": "Histoire d'Eau",
      "url": "https://bleau.info/beauvaisest/176746.html",
      "grade": "5+",
      "alt_grade": null,
      "first_ascensionist": null,
      "styles": [
        "traversée d-g"
      ],
      "rating": null
    },
    {
      "name": "Kiowa",
      "url": "https://bleau.info/beauvaisest/6761.html",
      "grade": "5+",
      "alt_grade": null,
      "first_ascensionist": null,
      "styles": [
        "traversée d-g"
      ],
      "rating": null
    },
    {
      "name": "L'Air de Rien",
      "url": "https://bleau.info/beauvaisest/13102.html",
      "grade": "5+",
      "alt_grade": "6a",
      "first_ascensionist": "Dominique Yvorel",
      "styles": [
        "dévers",
        "aplats"
      ],
      "rating": null
    },
    {
      "name": "L'Enfer Vert",
      "url": "https://bleau.info/beauvaisest/6769.html",
      "grade": "5+",
      "alt_grade": null,
      "first_ascensionist": null,
      "styles": [
        "mur"
      ],
      "rating": null
    },
    {
      "name": "L'Oryx",
      "url": "https://bleau.info/beauvaisest/6766.html",
      "grade": "5+",
      "alt_grade": null,
      "first_ascensionist": null,
      "styles": [
        "aplats"
      ],
      "rating": null
    },
    {
      "name": "La Croisade",
      "url": "https://bleau.info/beauvaisest/13040.html",
      "grade": "5+",
      "alt_grade": null,
      "first_ascensionist": "Franck Martinez",
      "styles": [
        "traversée g-d"
      ],
      "rating": null
    },
    {
      "name": "La Vache Folle",
      "url": "https://bleau.info/beauvaisest/6759.html",
      "grade": "5+",
      "alt_grade": null,
      "first_ascensionist": null,
      "styles": [
        "traversée g-d"
      ],
      "rating": null
    },
    {
      "name": "Lastminute.bloc",
      "url": "https://bleau.info/beauvaisest/13047.html",
      "grade": "5+",
      "alt_grade": "5",
      "first_ascensionist": "Franck Martinez",
      "styles": [
        "mur"
      ],
      "rating": null
    },
    {
      "name": "Le Mur du Silence",
      "url": "https://bleau.info/beauvaisest/6753.html",
      "grade": "5+",
      "alt_grade": null,
      "first_ascensionist": null,
      "styles": [
        "mur"
      ],
      "rating": null
    },
    {
      "name": "Le P'tit J'té",
      "url": "https://bleau.info/beauvaisest/6760.html",
      "grade": "5+",
      "alt_grade": null,
      "first_ascensionist": null,
      "styles": [
        "jeté"
      ],
      "rating": null
    },
    {
      "name": "Le Pivot",
      "url": "https://bleau.info/beauvaisest/13043.html",
      "grade": "5+",
      "alt_grade": null,
      "first_ascensionist": "Franck Martinez",
      "styles": [
        "traversée g-d",
        "dalle",
        "départ assis"
      ],
      "rating": null
    },
    {
      "name": "Le Temple du Ciel",
      "url": "https://bleau.info/beauvaisest/6763.html",
      "grade": "5+",
      "alt_grade": null,
      "first_ascensionist": null,
      "styles": [
        "mur"
      ],
      "rating": null
    },
    {
      "name": "Maudite Brosse",
      "url": "https://bleau.info/beauvaisest/13073.html",
      "grade": "5+",
      "alt_grade": null,
      "first_ascensionist": "Dominique Yvorel",
      "styles": [
        "traversée d-g"
      ],
      "rating": null
    },
    {
      "name": "Olé",
      "url": "https://bleau.info/beauvaisest/13109.html",
      "grade": "5+",
      "alt_grade": null,
      "first_ascensionist": "Dominique Yvorel",
      "styles": [
        "dévers",
        "aplats",
        "expo"
      ],
      "rating": null
    },
    {
      "name": "Pampryl",
      "url": "https://bleau.info/beauvaisest/13122.html",
      "grade": "5+",
      "alt_grade": null,
      "first_ascensionist": "Dominique Yvorel",
      "styles": [
        "dévers",
        "départ assis"
      ],
      "rating": null
    },
    {
      "name": "Poussée de Fièvre (assis)",
      "url": "https://bleau.info/beauvaisest/307459.html",
      "grade": "5+",
      "alt_grade": null,
      "first_ascensionist": "Pepito, Blokeur",
      "styles": [
        "mur",
        "départ assis"
      ],
      "rating": null
    },
    {
      "name": "Sénégal (assis)",
      "url": "https://bleau.info/beauvaisest/307447.html",
      "grade": "5+",
      "alt_grade": null,
      "first_ascensionist": "Pepito, Blokeur",
      "styles": [
        "mur",
        "départ assis"
      ],
      "rating": null
    },
    {
      "name": "Stat'tique",
      "url": "https://bleau.info/beauvaisest/6747.html",
      "grade": "5+",
      "alt_grade": null,
      "first_ascensionist": null,
      "styles": [
        "mur"
      ],
      "rating": null
    },
    {
      "name": "Translation de Vecteurs",
      "url": "https://bleau.info/beauvaisest/13103.html",
      "grade": "5+",
      "alt_grade": null,
      "first_ascensionist": "Dominique Yvorel",
      "styles": [
        "traversée d-g"
      ],
      "rating": null
    },
    {
      "name": "- [n°2 bis Rouge ED-]",
      "url": "https://bleau.info/beauvaisest/6749.html",
      "grade": "5+",
      "alt_grade": null,
      "first_ascensionist": null,
      "styles": [
        "traversée"
      ],
      "rating": null
    },
    {
      "name": "27,2 le Matin",
      "url": "https://bleau.info/beauvaisest/13125.html",
      "grade": "5",
      "alt_grade": null,
      "first_ascensionist": null,
      "styles": [
        "mur"
      ],
      "rating": null
    },
    {
      "name": "Bien Mur",
      "url": "https://bleau.info/beauvaisest/13070.html",
      "grade": "5",
      "alt_grade": null,
      "first_ascensionist": "Dominique Yvorel",
      "styles": [
        "mur"
      ],
      "rating": 3.0
    },
    {
      "name": "Bonsaï Bis",
      "url": "https://bleau.info/beauvaisest/13105.html",
      "grade": "5",
      "alt_grade": null,
      "first_ascensionist": "Dominique Yvorel",
      "styles": [
        "mur",
        "départ assis"
      ],
      "rating": null
    },
    {
      "name": "Craquante",
      "url": "https://bleau.info/beauvaisest/13139.html",
      "grade": "5",
      "alt_grade": null,
      "first_ascensionist": "Dominique Yvorel",
      "styles": [
        "mur"
      ],
      "rating": null
    },
    {
      "name": "Démangeaison",
      "url": "https://bleau.info/beauvaisest/13049.html",
      "grade": "5",
      "alt_grade": null,
      "first_ascensionist": "Franck Martinez",
      "styles": [
        "traversée g-d",
        "réta",
        "départ assis"
      ],
      "rating": null
    },
    {
      "name": "Dites 33 (assis)",
      "url": "https://bleau.info/beauvaisest/307509.html",
      "grade": "5",
      "alt_grade": null,
      "first_ascensionist": "Pepito, Blokeur",
      "styles": [
        "mur",
        "départ assis"
      ],
      "rating": 4.0
    },
    {
      "name": "Dos au Mur",
      "url": "https://bleau.info/beauvaisest/13116.html",
      "grade": "5",
      "alt_grade": null,
      "first_ascensionist": null,
      "styles": [
        "mur",
        "fissure"
      ],
      "rating": null
    },
    {
      "name": "Élimination",
      "url": "https://bleau.info/beauvaisest/13096.html",
      "grade": "5",
      "alt_grade": null,
      "first_ascensionist": "Dominique Yvorel",
      "styles": [
        "dalle"
      ],
      "rating": null
    },
    {
      "name": "Ippon",
      "url": "https://bleau.info/beauvaisest/13061.html",
      "grade": "5",
      "alt_grade": null,
      "first_ascensionist": "Franck Martinez",
      "styles": [
        "traversée g-d"
      ],
      "rating": null
    },
    {
      "name": "L'Apex",
      "url": "https://bleau.info/beauvaisest/13140.html",
      "grade": "5",
      "alt_grade": null,
      "first_ascensionist": "Dominique Yvorel",
      "styles": [
        "arête"
      ],
      "rating": null
    },
    {
      "name": "Non Voyant",
      "url": "https://bleau.info/beauvaisest/13115.html",
      "grade": "5",
      "alt_grade": null,
      "first_ascensionist": "Dominique Yvorel",
      "styles": [
        "dévers",
        "départ assis"
      ],
      "rating": null
    },
    {
      "name": "Autour du Pin",
      "url": "https://bleau.info/beauvaisest/13069.html",
      "grade": "5-",
      "alt_grade": null,
      "first_ascensionist": "Dominique Yvorel",
      "styles": [
        "traversée d-g"
      ],
      "rating": null
    },
    {
      "name": "Bord à Bord",
      "url": "https://bleau.info/beauvaisest/307516.html",
      "grade": "5-",
      "alt_grade": null,
      "first_ascensionist": "Pepito, Blokeur",
      "styles": [
        "pilier"
      ],
      "rating": 3.0
    },
    {
      "name": "Bouclier",
      "url": "https://bleau.info/beauvaisest/307442.html",
      "grade": "5-",
      "alt_grade": null,
      "first_ascensionist": "Pepito, Blokeur",
      "styles": [
        "dalle"
      ],
      "rating": 3.0
    },
    {
      "name": "Coup de Tabac",
      "url": "https://bleau.info/beauvaisest/307448.html",
      "grade": "5-",
      "alt_grade": null,
      "first_ascensionist": null,
      "styles": [
        "mur"
      ],
      "rating": 3.0
    },
    {
      "name": "Gaucherie",
      "url": "https://bleau.info/beauvaisest/13056.html",
      "grade": "5-",
      "alt_grade": null,
      "first_ascensionist": "Franck Martinez",
      "styles": [
        "traversée d-g",
        "surplomb"
      ],
      "rating": null
    },
    {
      "name": "L'Ami Hostile",
      "url": "https://bleau.info/beauvaisest/307454.html",
      "grade": "5-",
      "alt_grade": null,
      "first_ascensionist": null,
      "styles": [
        "mur"
      ],
      "rating": 3.0
    },
    {
      "name": "La Coquette",
      "url": "https://bleau.info/beauvaisest/307522.html",
      "grade": "5-",
      "alt_grade": null,
      "first_ascensionist": "Pepito, Blokeur",
      "styles": [
        "arête",
        "mur"
      ],
      "rating": 4.0
    },
    {
      "name": "La Disparition",
      "url": "https://bleau.info/beauvaisest/307451.html",
      "grade": "5-",
      "alt_grade": null,
      "first_ascensionist": "Pepito, Blokeur",
      "styles": [
        "mur"
      ],
      "rating": 3.0
    },
    {
      "name": "La Grenouille",
      "url": "https://bleau.info/beauvaisest/13126.html",
      "grade": "5-",
      "alt_grade": null,
      "first_ascensionist": "Dominique Yvorel",
      "styles": [
        "mur"
      ],
      "rating": null
    },
    {
      "name": "Pierre de Taille",
      "url": "https://bleau.info/beauvaisest/6750.html",
      "grade": "5-",
      "alt_grade": null,
      "first_ascensionist": null,
      "styles": [
        "arête"
      ],
      "rating": null
    },
    {
      "name": "Red Roof",
      "url": "https://bleau.info/beauvaisest/13111.html",
      "grade": "5-",
      "alt_grade": null,
      "first_ascensionist": null,
      "styles": [
        "surplomb",
        "départ assis"
      ],
      "rating": 3.0
    },
    {
      "name": "Retour aux Sources",
      "url": "https://bleau.info/beauvaisest/307523.html",
      "grade": "5-",
      "alt_grade": null,
      "first_ascensionist": "Pepito, Blokeur",
      "styles": [
        "mur"
      ],
      "rating": 4.0
    },
    {
      "name": "Spider Monkey",
      "url": "https://bleau.info/beauvaisest/13045.html",
      "grade": "5-",
      "alt_grade": null,
      "first_ascensionist": "Franck Martinez",
      "styles": [
        "mur",
        "arête"
      ],
      "rating": null
    },
    {
      "name": "Tamahak",
      "url": "https://bleau.info/beauvaisest/307450.html",
      "grade": "5-",
      "alt_grade": null,
      "first_ascensionist": null,
      "styles": [
        "mur"
      ],
      "rating": 4.0
    },
    {
      "name": "Yuko",
      "url": "https://bleau.info/beauvaisest/13060.html",
      "grade": "5-",
      "alt_grade": null,
      "first_ascensionist": "Franck Martinez",
      "styles": [
        "traversée d-g",
        "réta",
        "surplomb"
      ],
      "rating": null
    },
    {
      "name": "Celle de Gauche",
      "url": "https://bleau.info/beauvaisest/13119.html",
      "grade": "4+",
      "alt_grade": null,
      "first_ascensionist": null,
      "styles": [
        "fissure"
      ],
      "rating": 2.5
    },
    {
      "name": "Celle du Milieu",
      "url": "https://bleau.info/beauvaisest/13123.html",
      "grade": "4+",
      "alt_grade": null,
      "first_ascensionist": null,
      "styles": [
        "mur"
      ],
      "rating": null
    },
    {
      "name": "Coup de Boule",
      "url": "https://bleau.info/beauvaisest/307520.html",
      "grade": "4+",
      "alt_grade": null,
      "first_ascensionist": "Pepito, Blokeur",
      "styles": [
        "proue"
      ],
      "rating": 3.0
    },
    {
      "name": "Coup de Fatigue",
      "url": "https://bleau.info/beauvaisest/307460.html",
      "grade": "4+",
      "alt_grade": null,
      "first_ascensionist": null,
      "styles": [
        "pilier"
      ],
      "rating": 3.0
    },
    {
      "name": "Cuirasse",
      "url": "https://bleau.info/beauvaisest/307444.html",
      "grade": "4+",
      "alt_grade": null,
      "first_ascensionist": "Pepito, Blokeur",
      "styles": [
        "dévers",
        "départ assis"
      ],
      "rating": 3.0
    },
    {
      "name": "Dites 33",
      "url": "https://bleau.info/beauvaisest/13081.html",
      "grade": "4+",
      "alt_grade": null,
      "first_ascensionist": null,
      "styles": [
        "mur"
      ],
      "rating": 3.0
    },
    {
      "name": "Djibril",
      "url": "https://bleau.info/beauvaisest/13035.html",
      "grade": "4+",
      "alt_grade": null,
      "first_ascensionist": "Franck Martinez",
      "styles": [
        "traversée g-d"
      ],
      "rating": null
    },
    {
      "name": "Éole",
      "url": "https://bleau.info/beauvaisest/307449.html",
      "grade": "4+",
      "alt_grade": null,
      "first_ascensionist": null,
      "styles": [
        "mur"
      ],
      "rating": 3.5
    },
    {
      "name": "Fond de Taille",
      "url": "https://bleau.info/beauvaisest/13101.html",
      "grade": "4+",
      "alt_grade": null,
      "first_ascensionist": null,
      "styles": [
        "mur",
        "fissure"
      ],
      "rating": null
    },
    {
      "name": "Histoire d'Eau (direct)",
      "url": "https://bleau.info/beauvaisest/6762.html",
      "grade": "4+",
      "alt_grade": null,
      "first_ascensionist": null,
      "styles": [
        "dalle",
        "fissure"
      ],
      "rating": 4.0
    },
    {
      "name": "Le Pin",
      "url": "https://bleau.info/beauvaisest/13068.html",
      "grade": "4+",
      "alt_grade": null,
      "first_ascensionist": "Dominique Yvorel",
      "styles": [
        "mur",
        "départ assis"
      ],
      "rating": null
    },
    {
      "name": "Lichen Tenace",
      "url": "https://bleau.info/beauvaisest/13086.html",
      "grade": "4+",
      "alt_grade": null,
      "first_ascensionist": "Dominique Yvorel",
      "styles": [
        "dévers"
      ],
      "rating": null
    },
    {
      "name": "Météorite",
      "url": "https://bleau.info/beauvaisest/13038.html",
      "grade": "4+",
      "alt_grade": null,
      "first_ascensionist": "Franck Martinez",
      "styles": [
        "mur",
        "expo",
        "départ assis"
      ],
      "rating": null
    },
    {
      "name": "Petit Bon",
      "url": "https://bleau.info/beauvaisest/13066.html",
      "grade": "4+",
      "alt_grade": null,
      "first_ascensionist": "Dominique Yvorel",
      "styles": [
        "mur"
      ],
      "rating": 3.0
    },
    {
      "name": "Pour Rire",
      "url": "https://bleau.info/beauvaisest/13136.html",
      "grade": "4+",
      "alt_grade": null,
      "first_ascensionist": "Dominique Yvorel",
      "styles": [
        "traversée d-g"
      ],
      "rating": null
    },
    {
      "name": "Poussée de Fièvre",
      "url": "https://bleau.info/beauvaisest/307458.html",
      "grade": "4+",
      "alt_grade": null,
      "first_ascensionist": "Pepito, Blokeur",
      "styles": [
        "mur"
      ],
      "rating": 3.0
    },
    {
      "name": "Rêve d'Icare",
      "url": "https://bleau.info/beauvaisest/6765.html",
      "grade": "4+",
      "alt_grade": null,
      "first_ascensionist": null,
      "styles": [
        "jeté"
      ],
      "rating": null
    },
    {
      "name": "Sénégal",
      "url": "https://bleau.info/beauvaisest/307446.html",
      "grade": "4+",
      "alt_grade": "5-",
      "first_ascensionist": "Pepito, Blokeur",
      "styles": [
        "mur"
      ],
      "rating": 3.0
    },
    {
      "name": "Tête Dure",
      "url": "https://bleau.info/beauvaisest/307464.html",
      "grade": "4+",
      "alt_grade": null,
      "first_ascensionist": "Pepito, Blokeur",
      "styles": [
        "pilier"
      ],
      "rating": 3.5
    },
    {
      "name": "Tom et Jerry",
      "url": "https://bleau.info/beauvaisest/307443.html",
      "grade": "4+",
      "alt_grade": null,
      "first_ascensionist": null,
      "styles": [
        "traversée g-d",
        "dalle"
      ],
      "rating": 3.0
    },
    {
      "name": "Trentent",
      "url": "https://bleau.info/beauvaisest/13113.html",
      "grade": "4+",
      "alt_grade": null,
      "first_ascensionist": null,
      "styles": [
        "mur"
      ],
      "rating": null
    },
    {
      "name": "Afrique",
      "url": "https://bleau.info/beauvaisest/307445.html",
      "grade": "4",
      "alt_grade": null,
      "first_ascensionist": "Pepito",
      "styles": [
        "mur"
      ],
      "rating": 4.0
    },
    {
      "name": "Air Sec",
      "url": "https://bleau.info/beauvaisest/307463.html",
      "grade": "4",
      "alt_grade": null,
      "first_ascensionist": "Pepito, Blokeur",
      "styles": [
        "dalle"
      ],
      "rating": 3.0
    },
    {
      "name": "Alcôve",
      "url": "https://bleau.info/beauvaisest/307515.html",
      "grade": "4",
      "alt_grade": null,
      "first_ascensionist": "Pepito, Blokeur",
      "styles": [
        "mur",
        "départ assis"
      ],
      "rating": 3.0
    },
    {
      "name": "Champagne",
      "url": "https://bleau.info/beauvaisest/13106.html",
      "grade": "4",
      "alt_grade": null,
      "first_ascensionist": "Dominique Yvorel",
      "styles": [
        "mur"
      ],
      "rating": null
    },
    {
      "name": "Contremarche",
      "url": "https://bleau.info/beauvaisest/13095.html",
      "grade": "4",
      "alt_grade": null,
      "first_ascensionist": null,
      "styles": [
        "mur"
      ],
      "rating": null
    },
    {
      "name": "Fracture",
      "url": "https://bleau.info/beauvaisest/13078.html",
      "grade": "4",
      "alt_grade": null,
      "first_ascensionist": "Dominique Yvorel",
      "styles": [
        "mur",
        "fissure"
      ],
      "rating": null
    },
    {
      "name": "Gros Rouge 2007",
      "url": "https://bleau.info/beauvaisest/13077.html",
      "grade": "4",
      "alt_grade": null,
      "first_ascensionist": null,
      "styles": [
        "dévers"
      ],
      "rating": null
    },
    {
      "name": "La Confiscation",
      "url": "https://bleau.info/beauvaisest/307456.html",
      "grade": "4",
      "alt_grade": null,
      "first_ascensionist": "Pepito, Blokeur",
      "styles": [
        "pilier"
      ],
      "rating": 3.0
    },
    {
      "name": "Plat Tonique",
      "url": "https://bleau.info/beauvaisest/13052.html",
      "grade": "4",
      "alt_grade": null,
      "first_ascensionist": "Franck Martinez",
      "styles": [
        "traversée d-g",
        "aplats"
      ],
      "rating": null
    },
    {
      "name": "Premier Pas",
      "url": "https://bleau.info/beauvaisest/307517.html",
      "grade": "4",
      "alt_grade": null,
      "first_ascensionist": null,
      "styles": [
        "dalle"
      ],
      "rating": 3.0
    },
    {
      "name": "Swing",
      "url": "https://bleau.info/beauvaisest/307524.html",
      "grade": "4",
      "alt_grade": null,
      "first_ascensionist": "Pepito, Blokeur",
      "styles": [
        "mur"
      ],
      "rating": 3.0
    },
    {
      "name": "Tête à Tête",
      "url": "https://bleau.info/beauvaisest/307521.html",
      "grade": "4",
      "alt_grade": null,
      "first_ascensionist": "Pepito, Blokeur",
      "styles": [
        "proue",
        "départ assis"
      ],
      "rating": 3.0
    },
    {
      "name": "Air Doux",
      "url": "https://bleau.info/beauvaisest/307462.html",
      "grade": "4-",
      "alt_grade": null,
      "first_ascensionist": "Pepito, Blokeur",
      "styles": [
        "dalle"
      ],
      "rating": 3.0
    },
    {
      "name": "Annaboule",
      "url": "https://bleau.info/beauvaisest/13039.html",
      "grade": "4-",
      "alt_grade": null,
      "first_ascensionist": "Annabelle Perez",
      "styles": [
        "mur",
        "dalle",
        "départ assis"
      ],
      "rating": null
    },
    {
      "name": "Barre à Mine",
      "url": "https://bleau.info/beauvaisest/13104.html",
      "grade": "4-",
      "alt_grade": null,
      "first_ascensionist": "Dominique Yvorel",
      "styles": [
        "mur"
      ],
      "rating": null
    },
    {
      "name": "Carapace",
      "url": "https://bleau.info/beauvaisest/13041.html",
      "grade": "4-",
      "alt_grade": null,
      "first_ascensionist": "Franck Martinez",
      "styles": [
        "mur"
      ],
      "rating": 3.0
    },
    {
      "name": "Évidence",
      "url": "https://bleau.info/beauvaisest/13108.html",
      "grade": "4-",
      "alt_grade": null,
      "first_ascensionist": "Dominique Yvorel",
      "styles": [
        "arête"
      ],
      "rating": 3.0
    },
    {
      "name": "Histoire 2",
      "url": "https://bleau.info/beauvaisest/13053.html",
      "grade": "4-",
      "alt_grade": null,
      "first_ascensionist": "Franck Martinez",
      "styles": [],
      "rating": null
    },
    {
      "name": "Jerry",
      "url": "https://bleau.info/beauvaisest/13072.html",
      "grade": "4-",
      "alt_grade": null,
      "first_ascensionist": "Florian Yvorel",
      "styles": [
        "dalle"
      ],
      "rating": null
    },
    {
      "name": "Le Petit Prétentieux",
      "url": "https://bleau.info/beauvaisest/13037.html",
      "grade": "4-",
      "alt_grade": null,
      "first_ascensionist": "Laura Martinez",
      "styles": [
        "mur",
        "dalle"
      ],
      "rating": null
    },
    {
      "name": "Libre Choix",
      "url": "https://bleau.info/beauvaisest/13097.html",
      "grade": "4-",
      "alt_grade": null,
      "first_ascensionist": null,
      "styles": [
        "dalle"
      ],
      "rating": 3.0
    },
    {
      "name": "Mini Slab",
      "url": "https://bleau.info/beauvaisest/13085.html",
      "grade": "4-",
      "alt_grade": null,
      "first_ascensionist": "Dominique Yvorel",
      "styles": [
        "dalle",
        "mur"
      ],
      "rating": null
    },
    {
      "name": "Tierce",
      "url": "https://bleau.info/beauvaisest/13050.html",
      "grade": "4-",
      "alt_grade": null,
      "first_ascensionist": "Franck Martinez",
      "styles": [
        "mur",
        "expo"
      ],
      "rating": 4.0
    },
    {
      "name": "Celle de Droite",
      "url": "https://bleau.info/beauvaisest/13121.html",
      "grade": "3+",
      "alt_grade": null,
      "first_ascensionist": null,
      "styles": [
        "fissure"
      ],
      "rating": 2.0
    },
    {
      "name": "Dalle, Ya",
      "url": "https://bleau.info/beauvaisest/13076.html",
      "grade": "3+",
      "alt_grade": null,
      "first_ascensionist": "Dominique Yvorel",
      "styles": [
        "dalle"
      ],
      "rating": null
    },
    {
      "name": "Dépêche",
      "url": "https://bleau.info/beauvaisest/13042.html",
      "grade": "3+",
      "alt_grade": null,
      "first_ascensionist": "Franck Martinez",
      "styles": [
        "dalle"
      ],
      "rating": 3.0
    },
    {
      "name": "Fastoche",
      "url": "https://bleau.info/beauvaisest/13091.html",
      "grade": "3+",
      "alt_grade": null,
      "first_ascensionist": "Dominique Yvorel",
      "styles": [
        "arête"
      ],
      "rating": 3.0
    },
    {
      "name": "L'Échelle Volante",
      "url": "https://bleau.info/beauvaisest/307452.html",
      "grade": "3+",
      "alt_grade": null,
      "first_ascensionist": null,
      "styles": [
        "dévers"
      ],
      "rating": 3.0
    },
    {
      "name": "La Môme",
      "url": "https://bleau.info/beauvaisest/13092.html",
      "grade": "3+",
      "alt_grade": null,
      "first_ascensionist": "Dominique Yvorel",
      "styles": [
        "dalle"
      ],
      "rating": null
    },
    {
      "name": "Le Retardataire",
      "url": "https://bleau.info/beauvaisest/13055.html",
      "grade": "3+",
      "alt_grade": null,
      "first_ascensionist": "Franck Martinez",
      "styles": [
        "traversée g-d"
      ],
      "rating": null
    },
    {
      "name": "Montparnasse",
      "url": "https://bleau.info/beauvaisest/13048.html",
      "grade": "3+",
      "alt_grade": null,
      "first_ascensionist": "Laura Martinez",
      "styles": [
        "mur",
        "expo"
      ],
      "rating": 4.5
    },
    {
      "name": "Red Stair",
      "url": "https://bleau.info/beauvaisest/13107.html",
      "grade": "3+",
      "alt_grade": null,
      "first_ascensionist": null,
      "styles": [
        "arête"
      ],
      "rating": null
    },
    {
      "name": "Vite Fait",
      "url": "https://bleau.info/beauvaisest/13067.html",
      "grade": "3+",
      "alt_grade": null,
      "first_ascensionist": "Dominique Yvorel",
      "styles": [
        "dalle"
      ],
      "rating": null
    },
    {
      "name": "Vol Direct",
      "url": "https://bleau.info/beauvaisest/13128.html",
      "grade": "3+",
      "alt_grade": null,
      "first_ascensionist": "Dominique Yvorel",
      "styles": [
        "mur"
      ],
      "rating": null
    },
    {
      "name": "Relax",
      "url": "https://bleau.info/beauvaisest/13080.html",
      "grade": "3",
      "alt_grade": null,
      "first_ascensionist": "Dominique Yvorel",
      "styles": [
        "mur"
      ],
      "rating": null
    },
    {
      "name": "Tom",
      "url": "https://bleau.info/beauvaisest/13071.html",
      "grade": "3-",
      "alt_grade": null,
      "first_ascensionist": "Florian Yvorel",
      "styles": [
        "dalle"
      ],
      "rating": null
    },
    {
      "name": "Tour de Chauffe",
      "url": "https://bleau.info/beauvaisest/13036.html",
      "grade": "3-",
      "alt_grade": null,
      "first_ascensionist": "Franck Martinez",
      "styles": [
        "traversée d-g"
      ],
      "rating": null
    },
    {
      "name": "La Michtouille",
      "url": "https://bleau.info/beauvaisest/13054.html",
      "grade": "2+",
      "alt_grade": null,
      "first_ascensionist": "Franck Martinez",
      "styles": [],
      "rating": null
    },
    {
      "name": "Fingers in the Nose",
      "url": "https://bleau.info/beauvaisest/13074.html",
      "grade": "2",
      "alt_grade": null,
      "first_ascensionist": "Florian Yvorel",
      "styles": [
        "mur"
      ],
      "rating": null
    }
  ]
}